[
    {
        "images": [
            "test_ak_0000/with_hint.png",
            "test_ak_0000/without_hint.png",
            "test_ak_0000/without_brain.png"
        ],
        "n_aug": 10,
        "n_epoch": 10,
        "score no brain": [
            -4.8753045120975e-05,
            4.8753041482996196e-05
        ],
        "score w/ no hint": [
            -4.8804253310663626e-05,
            4.8804253310663626e-05
        ],
        "score_with_hints": [
            -4.880425694864243e-05,
            4.880425694864243e-05
        ]
    },
    {
        "images": [
            "test_ak_0001/with_hint.png",
            "test_ak_0001/without_hint.png",
            "test_ak_0001/without_brain.png"
        ],
        "n_aug": 10,
        "n_epoch": 10,
        "score no brain": [
            -6.50528963888064e-05,
            6.50528963888064e-05
        ],
        "score w/ no hint": [
            -6.509992090286687e-05,
            6.509992090286687e-05
        ],
        "score_with_hints": [
            -6.509992090286687e-05,
            6.509992090286687e-05
        ]
    }
]